printpop/__init__.py
printpop/color_printer.py
printpop/core.py
printpop-0.2.2.dist-info/METADATA
printpop-0.2.2.dist-info/WHEEL
printpop-0.2.2.dist-info/entry_points.txt
printpop-0.2.2.dist-info/RECORD
