Metadata-Version: 2.4
Name: printpop
Version: 0.2.2
Summary: Styled console printing made simple — color, format, and clickable hyperlinks in one package.
Project-URL: Homepage, https://github.com/rlapine/PrintPop
Project-URL: Documentation, https://github.com/rlapine/PrintPop/README.md
Project-URL: Repository, https://github.com/rlapine/PrintPop
Author-email: Ryan LaPine <github.stunt845@passinbox.com>
Maintainer-email: Ryan LaPine <github.stunt845@passinbox.com>
License: MIT
Keywords: CLI,color,console,formatting,hyperlink,logging,printing
Classifier: Intended Audience :: Developers
Classifier: License :: OSI Approved :: MIT License
Classifier: Operating System :: OS Independent
Classifier: Programming Language :: Python :: 3
Classifier: Topic :: Software Development :: Libraries
Classifier: Topic :: Utilities
Requires-Python: >=3.8
